{
   "mainPrompt": "Write {{aiName}}'s next reply in a fictional chat between {{aiName}} and {{playerName}}. Write 1 reply only in internet RP style, italicize actions, and avoid quotation marks. Use markdown. Be proactive, creative, and drive the plot and conversation forward. Write at least 1 paragraph, up to 4. Always stay in character and avoid repetition.",
   "inputSequence": "[INST]\n",
   "outputSequence": "[/INST]\n" ,
    "parameters": {
         "temperature": 0.9,
         "max_tokens": 300,
         "frequency_penalty": 0.7,
         "presence_penalty": 0.7
    }
 }
 